[
  {
    "id": 1782638342918,
    "submitted": "2026-06-28T09:19:02.918Z",
    "status": "new",
    "name": "Fran O'Reilly",
    "dob": "0001-01-01",
    "phone": "+353879948630",
    "email": "prunch@gmail.com",
    "conditions": [
      "Prevention Programme (PP)"
    ],
    "abpmConsent": "yes",
    "abpmSigned": "Fran O' Reilly",
    "fields": {
      "Full Name": "Fran O'Reilly",
      "Date of Birth": "0001-01-01",
      "Phone Number": "+353879948630",
      "Email Address": "prunch@gmail.com",
      "Prevention Programme (PP)": [
        "Prevention Programme (PP)"
      ],
      "Smoking status": "never",
      "Approximate alcohol intake (units per week)": "0 — I don't drink",
      "How many days per week do you do physical activity or exercise (at least 30 minutes)?": "0 days",
      "Any concerns about your diet you would like to discuss?": "No — diet is fine",
      "No": "No",
      "Any new family history of heart disease, stroke, or diabetes since your last visit?": "No changes",
      "Any other concerns you would like to discuss at your appointment?": "n",
      "overall health change": "No significant changes",
      "hospital admission": "No",
      "new diagnosis": "No",
      "Do you drink alcohol?": "no",
      "Any issues with your medications?": "n",
      "Health and Well-being — How would you describe this?": "Excellent — I feel very well",
      "My Health Goals": "m",
      "Weight": "00",
      "Waist Circumference": "00",
      "Any new medications added since your last visit?": "n",
      "ABPM Consent": "yes",
      "Full Name — Electronic Signature": "Fran O' Reilly"
    }
  },
  {
    "id": 1782580707274,
    "submitted": "2026-06-27T17:18:27.274Z",
    "status": "new",
    "name": "test",
    "dob": "0001-01-01",
    "phone": "+353879948630",
    "email": "prunch@gmail.com",
    "conditions": [
      "Prevention Programme (PP)"
    ],
    "abpmConsent": "no",
    "abpmSigned": "",
    "fields": {
      "Full Name": "test",
      "Date of Birth": "0001-01-01",
      "Phone Number": "+353879948630",
      "Email Address": "prunch@gmail.com",
      "Prevention Programme (PP)": [
        "Prevention Programme (PP)"
      ],
      "Smoking status": "never",
      "Approximate alcohol intake (units per week)": "0 — I don't drink",
      "How many days per week do you do physical activity or exercise (at least 30 minutes)?": "0 days",
      "Any concerns about your diet you would like to discuss?": "No — diet is fine",
      "No": "No",
      "Any new family history of heart disease, stroke, or diabetes since your last visit?": "No changes",
      "Any other concerns you would like to discuss at your appointment?": "no",
      "overall health change": "No significant changes",
      "hospital admission": "No",
      "new diagnosis": "No",
      "Do you drink alcohol?": "no",
      "Any issues with your medications?": "no",
      "Health and Well-being — How would you describe this?": "Good — generally feeling well",
      "My Health Goals": "no",
      "Weight": "00",
      "Waist Circumference": "00",
      "Any new medications added since your last visit?": "none",
      "ABPM Consent": "no"
    }
  },
  {
    "id": 1782580262812,
    "submitted": "2026-06-27T17:11:02.812Z",
    "status": "new",
    "name": "test",
    "dob": "0001-01-01",
    "phone": "+353879948630",
    "email": "prunch@gmail.com",
    "conditions": [
      "Hypertension"
    ],
    "abpmConsent": "no",
    "abpmSigned": "",
    "fields": {
      "Full Name": "test",
      "Date of Birth": "0001-01-01",
      "Phone Number": "+353879948630",
      "Email Address": "prunch@gmail.com",
      "Hypertension (High Blood Pressure)": [
        "Hypertension"
      ],
      "No": "No",
      "None of the above": [
        "None"
      ],
      "Approximate alcohol intake (units per week)": "0 — I don't drink",
      "Are you taking your blood pressure medication every day?": "Most days",
      "Any side effects from your medication you would like to discuss?": "no",
      "overall health change": "No significant changes",
      "hospital admission": "No",
      "new diagnosis": "No",
      "Smoking status": "never",
      "Do you drink alcohol?": "no",
      "Any issues with your medications?": "none",
      "Weight": "00",
      "Waist Circumference": "00",
      "Any new medications added since your last visit?": "none",
      "ABPM Consent": "no"
    }
  }
]